yoapi_cli/__init__.py
yoapi_cli/cli.py
yoapi_cli/commands/plugin.py
yoapi_cli/commands/run.py
yoapi_cli/commands/venv.py
yoapi_cli-0.1.8.dist-info/licenses/LICENSE
yoapi_cli-0.1.8.dist-info/METADATA
yoapi_cli-0.1.8.dist-info/WHEEL
yoapi_cli-0.1.8.dist-info/entry_points.txt
yoapi_cli-0.1.8.dist-info/top_level.txt
yoapi_cli-0.1.8.dist-info/RECORD
