Metadata-Version: 2.4
Name: yoapi-cli
Version: 0.1.8
Summary: WaveYo-API Command Line Interface Tool
Author-email: WaveYo Team <contact@waveyo.com>
License: MIT
Project-URL: Homepage, https://github.com/WaveYo/yoapi-cli
Project-URL: Repository, https://github.com/WaveYo/yoapi-cli
Project-URL: Documentation, https://github.com/WaveYo/yoapi-cli#readme
Project-URL: Issues, https://github.com/WaveYo/yoapi-cli/issues
Keywords: fastapi,cli,plugin,api,backend
Classifier: Development Status :: 4 - Beta
Classifier: Intended Audience :: Developers
Classifier: License :: OSI Approved :: MIT License
Classifier: Programming Language :: Python :: 3
Classifier: Programming Language :: Python :: 3.11
Classifier: Programming Language :: Python :: 3.12
Classifier: Programming Language :: Python :: 3.13
Classifier: Programming Language :: Python :: 3.14
Requires-Python: >=3.11
License-File: LICENSE
Requires-Dist: click>=8.0.0
Requires-Dist: requests>=2.25.0
Requires-Dist: python-dotenv>=0.19.0
Requires-Dist: GitPython>=3.1.0
Requires-Dist: rich>=10.0.0
Requires-Dist: typer>=0.9.0
Provides-Extra: dev
Requires-Dist: pytest>=6.0.0; extra == "dev"
Requires-Dist: pytest-cov>=3.0.0; extra == "dev"
Requires-Dist: black>=22.0.0; extra == "dev"
Requires-Dist: isort>=5.0.0; extra == "dev"
Requires-Dist: flake8>=4.0.0; extra == "dev"
Requires-Dist: mypy>=0.900; extra == "dev"
Requires-Dist: nuitka>=1.0.0; extra == "dev"
Dynamic: license-file
